[
  {
    "locationName": "Light Woods",
    "goalWords":
    [
      "JOY",
      "HAY",
      "SUN",
      "FREE",
      "GEM",
      "CAT",
      "HEAT",
      "RUN",
      "RAY",
      "BOW",
      "HOLY",
      "FAY",
      "DOVE",
      "FUN",
      "KEEP",
      "MAY",
      "NUT",
      "LAWN",
      "DOG",
      "FLY",
      "MEAL",
      "HERB",
      "MAP",
      "MOOD",
      "FAR",
      "FOX",
      "LONG",
      "WAY",
      "DAY",
      "BIG",
      "GOD",
      "HUG",
      "TENT",
      "JAY",
      "KID",
      "PAW",
      "AIR",
      "OUT",
      "ELF",
      "ROD",
      "OAK",
      "OWL"
    ]
  },

  {
    "locationName": "Dark Woods",
    "goalWords":
    [
      "ROCK",
      "DARK",
      "HOPE",
      "TREE",
      "HAZE",
      "CROW",
      "WILD",
      "WIND",
      "RAIN",
      "CAMP",
      "BEAR",
      "ROAR",
      "WEAK",
      "LEAF",
      "CARE",
      "FEET",
      "FEAR",
      "TEAR",
      "STEP",
      "FIND",
      "HARD",
      "GRAY",
      "COLD",
      "DEER",
      "DEEP",
      "LOST",
      "PAST",
      "WOOD",
      "TALE",
      "FANG",
      "LATE",
      "SAME",
      "SANE",
      "WILL",
      "LAND",
      "NEAR",
      "HELP",
      "LIFE",
      "GONE",
      "CALL",
      "BOOK",
      "BIRD",
      "SONG",
      "FIRE",
      "WAND",
      "HAND",
      "MISS",
      "LEAD",
      "TEAM",
      "WEEK",
      "WEST"
    ]

  },

  {
    "locationName" : "Moon Lake",
    "goalWords":
    [
      "MOON",
      "LAKE",
      "STAR",
      "FISH",
      "DIVE",
      "DEEP",
      "WISH",
      "BLUE",
      "LUCK",
      "LIVE",
      "SAFE",
      "SING",
      "SOUL",
      "SWIM",
      "SWAN",
      "TAKE",
      "RING",
      "RARE",
      "CALM",
      "WAVE",
      "WARM",
      "SOFT",
      "TRIP",
      "RISE",
      "SAVE",
      "NEED",
      "FEEL",
      "FLOW",
      "NAME",
      "JUMP",
      "SAND",
      "SOIL",
      "RICH",
      "GAME",
      "LINE",
      "SPOT",
      "DUCK",
      "SLIP",
      "SEAT",
      "MADE",
      "PRAY",
      "LOVE",
      "FATE",
      "FADE",
      "CAGE",
      "TIME",
      "FROG",
      "PATH",
      "PLUM",
      "BALL",
      "MILD",
      "BACK",
      "KIND"
    ]
  },

  {
    "locationName" : "Cursed Swamp",
    "goalWords" :
    [
      "TRAP",
      "SWAMP",
      "HATE",
      "SLEEP",
      "HIDE",
      "WITCH",
      "SEEK",
      "STUCK",
      "FALL",
      "SPELL",
      "HELP",
      "SHOUT",
      "STAY",
      "ROUGH",
      "LOSE",
      "SCARY",
      "LAST",
      "EVIL",
      "STORY",
      "NIGHT",
      "FIGHT",
      "FAKE",
      "BOAT",
      "DOWN",
      "RAGE",
      "COAT",
      "LEAK",
      "COLD",
      "ROPE",
      "MOTH",
      "PLACE",
      "CLOUD",
      "COPE",
      "CODE",
      "WORD",
      "OVER",
      "BRAVE",
      "MINE",
      "AWAY",
      "TALK",
      "ROAD",
      "MESS",
      "DROP",
      "DUST",
      "FAST",
      "HURT",
      "PAIN",
      "BREAK",
      "CREEP",
      "LACK",
      "PLANT",
      "PALE",
      "SKULL",
      "GRIM",
      "MOLD",
      "RISK",
      "NASTY",
      "STICK",
      "WEARY",
      "ALONE",
      "SHAME",
      "WORM",
      "FAITH",
      "FENCE",
      "MIGHT",
      "PLACE",
      "STONE",
      "SNAKE",
      "SPIKE",
      "TRACE",
      "BLAME",
      "SMELL",
      "STEAM",
      "MIST",
      "SLOW"

    ]
  },

  {
    "locationName": "Fairy Meadow",
    "goalWords":
    [
      "GATE",
      "PEAR",
      "PINK",
      "COIN",
      "SNAP",
      "WELL",
      "LACE",
      "SAGE",
      "HEAL",
      "CURE",
      "JADE",
      "STEM",
      "ROSE",
      "CROWN",
      "AWARD",
      "BLESS",
      "COVER",
      "BLOOM",
      "BLISS",
      "TINY",
      "BALM",
      "CHARM",
      "CLEAN",
      "DREAM",
      "CARD",
      "GRACE",
      "BEAM",
      "LIGHT",
      "KEEN",
      "HILL",
      "MUSE",
      "SHANE",
      "FINE",
      "GIFT",
      "DAISY",
      "SWEET",
      "LARK",
      "MAGIC",
      "NOTE",
      "MAZE",
      "PEAK",
      "CLOVE",
      "PEACH",
      "FLICK",
      "RIVER",
      "TIDY",
      "SMALL",
      "TRUE",
      "SNAIL",
      "ZEST",
      "TOWER",
      "NOON",
      "BLIND",
      "DOUGH",
      "TRICK",
      "WING",
      "FAIRY",
      "FLARE",
      "FLAME",
      "SHAPE",
      "CATCH",
      "CUTE",
      "SHEEP",
      "LIKE",
      "BLAND",
      "KISS",
      "TOUCH",
      "GLOW",
      "BLUSH",
      "GRACE",
      "BLINK",
      "BUSH",
      "NEAT",
      "CLAP",
      "PURE",
      "WALK",
      "YARD",
      "CARE",
      "FAIR",
      "JOKE",
      "WISE",
      "PEACE",
      "COSY",
      "REST",
      "TALE",
      "MINT"

    ]
  },

  {
    "locationName": "Dragon Cliff",
    "goalWords":
    [
      "TOUGH",
      "CAVE",
      "CLIMB",
      "CRUSH",
      "SPITE",
      "TRIBE",
      "GLIDE",
      "SPLIT",
      "GLORY",
      "SLIDE",
      "GREAT",
      "SLOPE",
      "GRAND",
      "GUSTS",
      "SWING",
      "SHIFT",
      "ARISE",
      "LARGE",
      "DWELL",
      "CHASE",
      "RIDGE",
      "WRECK",
      "NOBLE",
      "RUNE",
      "FIRE",
      "FROST",
      "GLEAM",
      "BLAST",
      "LUNAR",
      "FLOAT",
      "ROYAL",
      "RIVAL",
      "SPOOK",
      "LOGIC",
      "FERAL",
      "SNARE",
      "HEATH",
      "BLEAK",
      "FROWN",
      "GLOOM",
      "NIGHT",
      "PRIME",
      "MYTH",
      "HERO",
      "GOLD",
      "RUBY",
      "LOOT",
      "TALL",
      "DARE",
      "PEAL",
      "EPIC",
      "CRAG",
      "SCAR",
      "BAWL",
      "HIGH",
      "CLAWS",
      "SWIFT",
      "SCARE"

    ]
  }
]